ovos_utterance_normalizer/__init__.py
ovos_utterance_normalizer/normalizer.py
ovos_utterance_normalizer/numeric.py
ovos_utterance_normalizer/tokenization.py
ovos_utterance_normalizer/version.py
ovos_utterance_normalizer/res/az/normalize.json
ovos_utterance_normalizer/res/ca/normalize.json
ovos_utterance_normalizer/res/cz/normalize.json
ovos_utterance_normalizer/res/de/normalize.json
ovos_utterance_normalizer/res/en/normalize.json
ovos_utterance_normalizer/res/es/normalize.json
ovos_utterance_normalizer/res/fr/normalize.json
ovos_utterance_normalizer/res/it/normalize.json
ovos_utterance_normalizer/res/nl/normalize.json
ovos_utterance_normalizer/res/no/normalize.json
ovos_utterance_normalizer/res/pt/normalize.json
ovos_utterance_normalizer/res/ru/normalize.json
ovos_utterance_normalizer/res/sl/normalize.json
ovos_utterance_normalizer/res/sv/normalize.json
ovos_utterance_normalizer/res/uk/normalize.json
ovos_utterance_normalizer-0.2.3.dist-info/licenses/LICENSE
ovos_utterance_normalizer-0.2.3.dist-info/METADATA
ovos_utterance_normalizer-0.2.3.dist-info/WHEEL
ovos_utterance_normalizer-0.2.3.dist-info/entry_points.txt
ovos_utterance_normalizer-0.2.3.dist-info/top_level.txt
ovos_utterance_normalizer-0.2.3.dist-info/zip-safe
ovos_utterance_normalizer-0.2.3.dist-info/RECORD
