Metadata-Version: 2.4
Name: ovos-utterance-normalizer
Version: 0.2.3
Home-page: https://github.com/OpenVoiceOS/ovos-utterance-normalizer
Author: jarbasai
Author-email: jarbasai@mailfence.com
License: apache-2.0
Classifier: Development Status :: 3 - Alpha
Classifier: Intended Audience :: Developers
Classifier: Topic :: Text Processing :: Linguistic
Classifier: License :: OSI Approved :: Apache Software License
Classifier: Programming Language :: Python :: 3.4
Classifier: Programming Language :: Python :: 3.5
Classifier: Programming Language :: Python :: 3.6
License-File: LICENSE
Requires-Dist: ovos-utils>=0.0.38
Requires-Dist: quebra-frases
Requires-Dist: ovos-plugin-manager<3.0.0,>=0.0.25
Requires-Dist: ftfy
Dynamic: author
Dynamic: author-email
Dynamic: classifier
Dynamic: description
Dynamic: description-content-type
Dynamic: home-page
Dynamic: license
Dynamic: license-file
Dynamic: requires-dist
